colemen_config.py
colemen_utils.py
colemen_utilities/parse_sql.py
colemen_utilities/parse_utils.py
colemen_utilities/build_utils/__init__.py
colemen_utilities/build_utils/general.py
colemen_utilities/build_utils/init_compiler.py
colemen_utilities/console_utils/__init__.py
colemen_utilities/console_utils/print.py
colemen_utilities/database_utils/DatabaseManager.py
colemen_utilities/database_utils/TableDataManager.py
colemen_utilities/database_utils/TableManager.py
colemen_utilities/database_utils/__init__.py
colemen_utilities/database_utils/MySQL/CacheFile.py
colemen_utilities/database_utils/MySQL/DatabaseManager.py
colemen_utilities/database_utils/MySQL/DeleteQuery.py
colemen_utilities/database_utils/MySQL/InsertQuery.py
colemen_utilities/database_utils/MySQL/MySQLDatabase.py
colemen_utilities/database_utils/MySQL/QueryBase.py
colemen_utilities/database_utils/MySQL/SelectQuery.py
colemen_utilities/database_utils/MySQL/UpdateQuery.py
colemen_utilities/database_utils/MySQL/__init__.py
colemen_utilities/database_utils/MySQL/Column/Column.py
colemen_utilities/database_utils/MySQL/Column/__init__.py
colemen_utilities/database_utils/MySQL/Column/column_utils.py
colemen_utilities/database_utils/MySQL/Relationship/Relationship.py
colemen_utilities/database_utils/MySQL/Relationship/__init__.py
colemen_utilities/database_utils/MySQL/Table/Table.py
colemen_utilities/database_utils/MySQL/Table/__init__.py
colemen_utilities/database_utils/drawio/ForeignKey.py
colemen_utilities/database_utils/drawio/Parser.py
colemen_utilities/database_utils/drawio/Row.py
colemen_utilities/database_utils/drawio/Schema.py
colemen_utilities/database_utils/drawio/Table.py
colemen_utilities/database_utils/drawio/__init__.py
colemen_utilities/database_utils/drawio/entity_utils.py
colemen_utilities/dict_utils/__init__.py
colemen_utilities/dict_utils/dict_utils.py
colemen_utilities/directory_utils/__init__.py
colemen_utilities/directory_utils/dir.py
colemen_utilities/directory_utils/dir_compression.py
colemen_utils-2.23.101.dist-info/METADATA
colemen_utils-2.23.101.dist-info/WHEEL
colemen_utils-2.23.101.dist-info/top_level.txt
colemen_utils-2.23.101.dist-info/RECORD
