Metadata-Version: 2.1
Name: colemen-utils
Version: 2.23.101
Summary: Colemen Utils
Author: Colemen Atwood
Author-email: <atwoodcolemen@gmail.com>
Keywords: python
Classifier: Development Status :: 3 - Alpha
Classifier: Intended Audience :: Education
Classifier: Programming Language :: Python :: 2
Classifier: Programming Language :: Python :: 3
Classifier: Operating System :: MacOS :: MacOS X
Classifier: Operating System :: Microsoft :: Windows
Requires-Dist: secure-delete
Requires-Dist: ftputil
Requires-Dist: ffmpeg-python
Requires-Dist: pillow
Requires-Dist: faker
Requires-Dist: iptcinfo3
Requires-Dist: patool
Requires-Dist: pyparsing
Requires-Dist: sqlparse
Requires-Dist: colorama
Requires-Dist: lxml
Requires-Dist: mysql-connector-python
Requires-Dist: exrex
Requires-Dist: pyyaml
Requires-Dist: inflect
Requires-Dist: cerberus
Requires-Dist: pyexiftool
Requires-Dist: win32-setctime
